Metadata-Version: 1.0
Name: ruitestpackage3
Version: 0.0.1
Summary: This is test package.
Home-page: UNKNOWN
Author: UNKNOWN
Author-email: UNKNOWN
License: UNKNOWN
Platform: UNKNOWN
